<?xml version="1.0" encoding="UTF-8" standalone="no"?><annotation>
	<folder>Poles</folder>
	<filename>RVX13EKB_20140726_211234_0082.xml</filename>
	<path>C:\Users\NSE4CLJ\Desktop\Poles\RVX13EKB_20140726_211234_f000801.png</path>
	<source>
		<database>Unknown</database>
	</source>
	<size>
		<width>1280</width>
		<height>720</height>
		<depth>1</depth>
	</size>
	<segmented>0</segmented>
	<object>
		<name>pole</name>
		<pose>Unspecified</pose>
		<truncated>0</truncated>
		<difficult>0</difficult>
		<bndbox>
			<xmin>988</xmin>
			<ymin>199</ymin>
			<xmax>1003</xmax>
			<ymax>542</ymax>
		</bndbox>
	</object>
	<object>
		<name>pole</name>
		<pose>Unspecified</pose>
		<truncated>0</truncated>
		<difficult>0</difficult>
		<bndbox>
			<xmin>253</xmin>
			<ymin>110</ymin>
			<xmax>276</xmax>
			<ymax>425</ymax>
		</bndbox>
	</object>
</annotation>