<annotation>
	<folder>Positive Gray</folder>
	<filename>AUDI-A4YH_20131001_083932_0382.bmp</filename>
	<path>/Users/nascasergiualin/Documents/GitHub/Pole-Detection/Positive Gray/AUDI-A4YH_20131001_083932_0382.bmp</path>
	<source>
		<database>Unknown</database>
	</source>
	<size>
		<width>1280</width>
		<height>720</height>
		<depth>1</depth>
	</size>
	<segmented>0</segmented>
	<object>
		<name>pole</name>
		<pose>Unspecified</pose>
		<truncated>0</truncated>
		<difficult>0</difficult>
		<bndbox>
			<xmin>1105</xmin>
			<ymin>34</ymin>
			<xmax>1122</xmax>
			<ymax>367</ymax>
		</bndbox>
	</object>
	<object>
		<name>pole</name>
		<pose>Unspecified</pose>
		<truncated>0</truncated>
		<difficult>0</difficult>
		<bndbox>
			<xmin>434</xmin>
			<ymin>150</ymin>
			<xmax>453</xmax>
			<ymax>402</ymax>
		</bndbox>
	</object>
	<object>
		<name>pole</name>
		<pose>Unspecified</pose>
		<truncated>0</truncated>
		<difficult>0</difficult>
		<bndbox>
			<xmin>782</xmin>
			<ymin>235</ymin>
			<xmax>792</xmax>
			<ymax>321</ymax>
		</bndbox>
	</object>
	<object>
		<name>pole</name>
		<pose>Unspecified</pose>
		<truncated>0</truncated>
		<difficult>0</difficult>
		<bndbox>
			<xmin>389</xmin>
			<ymin>257</ymin>
			<xmax>398</xmax>
			<ymax>366</ymax>
		</bndbox>
	</object>
	<object>
		<name>pole</name>
		<pose>Unspecified</pose>
		<truncated>0</truncated>
		<difficult>0</difficult>
		<bndbox>
			<xmin>660</xmin>
			<ymin>285</ymin>
			<xmax>666</xmax>
			<ymax>348</ymax>
		</bndbox>
	</object>
	<object>
		<name>pole</name>
		<pose>Unspecified</pose>
		<truncated>0</truncated>
		<difficult>0</difficult>
		<bndbox>
			<xmin>198</xmin>
			<ymin>280</ymin>
			<xmax>205</xmax>
			<ymax>341</ymax>
		</bndbox>
	</object>
	<object>
		<name>pole</name>
		<pose>Unspecified</pose>
		<truncated>0</truncated>
		<difficult>1</difficult>
		<bndbox>
			<xmin>95</xmin>
			<ymin>239</ymin>
			<xmax>108</xmax>
			<ymax>331</ymax>
		</bndbox>
	</object>
</annotation>
